Workbook

Sheet Farmer ROI
A1: Farmer Affordability & Illustrative Income Return — Benchmark & Sensitivity
A2: Input / Metric | B2: Value | C2: Unit | D2: Interpretation / Use | E2: Source
A3: Baseline monthly income — SunCulture women customers | B3: 184 | C3: USD / month | D3: 2026 Gender RBF benchmark; used only as an illustrative customer-income baseline. | E3: S2
A4: Share reporting income increase | B4: 0.79 | C4: % of women customers | D4: Observed in the 2026 SunCulture Gender RBF impact assessment. | E4: S2
A5: Weighted uplift among customers reporting gains | B5: 0.462 | C5: % uplift | D5: CrossBoundary calculation from the distribution of reported income gains. | E5: S2
A6: Expected uplift across income-generating customers | B6: =B4*B5 -> 0.36498 | C6: % uplift | D6: Population-weighted benchmark = share with gains × weighted uplift among gainers. | E6: S2
A7: USD / KES exchange rate | B7: 129.45 | C7: KES per USD | D7: Official CBK USD/KES daily rate posted 11 Sep 2026; used as a near-date translation for the 14 Sep case pricing baseline. | E7: S3
A8: Baseline monthly income | B8: =B3*B7 -> 23818.8 | C8: KES / month | D8: Converted external benchmark; not a case-provided farmer income figure. | E8: S2 + S3
A9: Base expected monthly incremental income | B9: =B8*B6 -> 8693.3856 | C9: KES / month | D9: Illustrative benchmark income gain used for repayment-capacity testing. | E9: S2 + S3
A10: Base expected post-adoption income | B10: =B8+B9 -> 32512.186 | C10: KES / month | D10: Baseline income plus modeled incremental income. | E10: S2 + S3
A11: Affordability payment-share heuristic | B11: 0.353 | C11: % of monthly income | D11: SunCulture 2021 illustration; treated as a heuristic, not a formal underwriting cutoff. | E11: S4
A12: Entry-level PAYGrow monthly payment | B12: 3900 | C12: KES / month | D12: RainMaker2S + CSD2 case pricing. | E12: S1
A13: Entry-level PAYGrow deposit | B13: 3999 | C13: KES | D13: RainMaker2S + CSD2 case pricing. | E13: S1
A14: Entry-level cash price | B14: 64999 | C14: KES | D14: RainMaker2S + CSD2 case pricing. | E14: S1
A15: Monthly payment / baseline income | B15: =B12/B8 -> 0.16373621 | C15: % of income | D15: Affordability indicator for the entry-level plan. | E15: Model
A16: Base incremental income coverage | B16: =B9/B12 -> 2.2290732 | C16: x | D16: How many times benchmark incremental monthly income covers the installment. | E16: Model
A17: Benchmark income uplift less installment | B17: =B9-B12 -> 4793.3856 | C17: KES / month | D17: Illustrative income uplift less PAYGrow monthly payment; this is not net profit and excludes added farm costs and seasonal timing. | E17: Model
A18: Simple cash-price payback | B18: =B14/B9 -> 7.4768339 | C18: months | D18: Cash price divided by modeled incremental monthly income; illustrative, not causal. | E18: Model
A19: Annual incremental income / cash price | B19: =B9*12/B14 -> 1.6049574 | C19: % | D19: Annualized benchmark incremental income divided by cash price. This is an income-to-price ratio, not ROI or net profit. | E19: Model
A20: Implied monthly income at 35.3% heuristic | B20: =B12/B11 -> 11048.159 | C20: KES / month | D20: Supplementary company heuristic only; 35.3% is not a disclosed underwriting cutoff or an external affordability standard. | E20: Model
A22: Income-Uplift Sensitivity — Entry-Level RainMaker2S + CSD2
A23: Scenario | B23: Construction | C23: Expected Uplift % | D23: Incremental Income (KES/mo) | E23: Installment Coverage | F23: Income Uplift Less Installment (KES/mo) | G23: Cash Payback (mo) | H23: Annual Incremental Income / Cash Price
A24: Conservative | B24: 79% × 12.5% (midpoint of lowest reported uplift band) | C24: =$B$4*12.5% -> 0.09875 | D24: =$B$8*C24 -> 2352.1065 | E24: =D24/$B$12 -> 0.60310423 | F24: =D24-$B$12 -> -1547.8935 | G24: =IF(D24>0,$B$14/D24,"") -> 27.634378 | H24: =IF(D24>0,D24*12/$B$14,"") -> 0.43424173
A25: Base | B25: 79% × 46.2% (weighted reported uplift among gainers) | C25: =$B$4*$B$5 -> 0.36498 | D25: =$B$8*C25 -> 8693.3856 | E25: =D25/$B$12 -> 2.2290732 | F25: =D25-$B$12 -> 4793.3856 | G25: =IF(D25>0,$B$14/D25,"") -> 7.4768339 | H25: =IF(D25>0,D25*12/$B$14,"") -> 1.6049574
A26: Upside | B26: 79% × 63% (midpoint of 51–75% reported uplift band) | C26: =$B$4*63% -> 0.4977 | D26: =$B$8*C26 -> 11854.617 | E26: =D26/$B$12 -> 3.0396453 | F26: =D26-$B$12 -> 7954.6168 | G26: =IF(D26>0,$B$14/D26,"") -> 5.4830115 | H26: =IF(D26>0,D26*12/$B$14,"") -> 2.1885783
A28: Evidence Interpretation / Modeling Limits
A29: Issue | B29: Implication
A30: External benchmark scope | B30: The $184 baseline income and 36.5% expected uplift come from a 2026 Gender RBF assessment of SunCulture women customers, not the full SunCulture customer base. Treat the scenario as a benchmark, not a population forecast.
A31: Independent evidence check | B31: A 2026 Duke/University of Nairobi panel evaluation (753 households) found encouraging welfare/adaptation effects, but short-run direct effects on total income and agricultural output were limited or statistically insignificant.
A32: Seasonality | B32: Agricultural cash flow is seasonal. The PAYGrow contract is monthly, but converting farm income into a smooth monthly equivalent can overstate month-to-month repayment liquidity; actual repayment capacity depends on harvest timing and shocks.
A33: Unmodeled farm costs | B33: Incremental seeds, fertilizer, hired labor, water access, crop-price volatility and other production costs are not deducted because product-specific public data are unavailable.
A34: Return metric interpretation | B34: Payback and annual income-to-price ratios are simple scenario metrics, not observed product ROI. They do not deduct incremental farm inputs/labor, financing cost, O&M, depreciation, or residual value.

Sheet PAYGrow Economics
A1: PAYGrow Economics — Contractual Collections, Affordability & Collection Sensitivity
A2: Key Metric | B2: Result | C2: Interpretation
A3: Entry-level upfront cash reduction | B3: =G9 -> 0.93847598 | C3: Deposit vs. cash price for RainMaker2S + CSD2.
A4: Comparable-product contractual premium range | B4: =TEXT(MIN(I9:I11),"0.0%")&" to "&TEXT(MAX(I9:I11),"0.0%") -> 85.6% to 95.1% | C4: Total contractual collections above stated cash price; not profit.
A5: Monthly payment / benchmark baseline income range | B5: =TEXT(MIN(J9:J15),"0.0%")&" to "&TEXT(MAX(J9:J15),"0.0%") -> 16.4% to 24.8% | C5: Illustrative affordability range across all financed products.
A6: Base income-uplift coverage range | B6: =TEXT(MIN(K9:K15),"0.00x")&" to "&TEXT(MAX(K9:K15),"0.00x") -> 1.47x to 2.23x | C6: Benchmark incremental monthly income divided by monthly installment.
A8: Product | B8: Deposit (KES) | C8: Monthly Payment (KES) | D8: Tenor (mo) | E8: Total Contractual Collections (KES) | F8: Cash Price (KES) | G8: Upfront Reduction % | H8: Contractual Premium (KES) | I8: Premium % | J8: Payment / Benchmark Income | K8: Base Uplift Coverage | L8: Uplift Less Payment (KES) | M8: Cash Payback (mo) | N8: Annual Income / Cash Price | O8: Deposit / Contract Value | P8: Source
A9: RainMaker2S + CSD2 | B9: 3999 | C9: 3900 | D9: 30 | E9: =B9+C9*D9 -> 120999 | F9: 64999 | G9: =IF(F9="","",1-B9/F9) -> 0.93847598 | H9: =IF(F9="","",E9-F9) -> 56000 | I9: =IF(F9="","",H9/F9) -> 0.86155172 | J9: =C9/'Farmer ROI'!$B$8 -> 0.16373621 | K9: ='Farmer ROI'!$B$9/C9 -> 2.2290732 | L9: ='Farmer ROI'!$B$9-C9 -> 4793.3856 | M9: =IF(F9="","",F9/'Farmer ROI'!$B$9) -> 7.4768339 | N9: =IF(F9="","",'Farmer ROI'!$B$9*12/F9) -> 1.6049574 | O9: =IF(E9=0,"",B9/E9) -> 0.03304986 | P9: S1
A10: RainMaker Kubwa MAX + CSD2 | B10: 5199 | C10: 4900 | D10: 30 | E10: =B10+C10*D10 -> 152199 | F10: 81999 | G10: =IF(F10="","",1-B10/F10) -> 0.93659679 | H10: =IF(F10="","",E10-F10) -> 70200 | I10: =IF(F10="","",H10/F10) -> 0.856108 | J10: =C10/'Farmer ROI'!$B$8 -> 0.20571985 | K10: ='Farmer ROI'!$B$9/C10 -> 1.7741603 | L10: ='Farmer ROI'!$B$9-C10 -> 3793.3856 | M10: =IF(F10="","",F10/'Farmer ROI'!$B$9) -> 9.4323436 | N10: =IF(F10="","",'Farmer ROI'!$B$9*12/F10) -> 1.2722183 | O10: =IF(E10=0,"",B10/E10) -> 0.034159226 | P10: S1
A11: RainMaker2S MAX + CSD2 | B11: 5199 | C11: 4900 | D11: 30 | E11: =B11+C11*D11 -> 152199 | F11: 77999 | G11: =IF(F11="","",1-B11/F11) -> 0.9333453 | H11: =IF(F11="","",E11-F11) -> 74200 | I11: =IF(F11="","",H11/F11) -> 0.95129425 | J11: =C11/'Farmer ROI'!$B$8 -> 0.20571985 | K11: ='Farmer ROI'!$B$9/C11 -> 1.7741603 | L11: ='Farmer ROI'!$B$9-C11 -> 3793.3856 | M11: =IF(F11="","",F11/'Farmer ROI'!$B$9) -> 8.9722236 | N11: =IF(F11="","",'Farmer ROI'!$B$9*12/F11) -> 1.3374611 | O11: =IF(E11=0,"",B11/E11) -> 0.034159226 | P11: S1
A12: Surface Pump + CSD1 | B12: 4899 | C12: 4900 | D12: 24 | E12: =B12+C12*D12 -> 122499 | G12: =IF(F12="","",1-B12/F12) | H12: =IF(F12="","",E12-F12) | I12: =IF(F12="","",H12/F12) | J12: =C12/'Farmer ROI'!$B$8 -> 0.20571985 | K12: ='Farmer ROI'!$B$9/C12 -> 1.7741603 | L12: ='Farmer ROI'!$B$9-C12 -> 3793.3856 | M12: =IF(F12="","",F12/'Farmer ROI'!$B$9) | N12: =IF(F12="","",'Farmer ROI'!$B$9*12/F12) | O12: =IF(E12=0,"",B12/E12) -> 0.039992163 | P12: S1
A13: RainMaker2S + CSB2 | B13: 8099 | C13: 5900 | D13: 36 | E13: =B13+C13*D13 -> 220499 | G13: =IF(F13="","",1-B13/F13) | H13: =IF(F13="","",E13-F13) | I13: =IF(F13="","",H13/F13) | J13: =C13/'Farmer ROI'!$B$8 -> 0.24770349 | K13: ='Farmer ROI'!$B$9/C13 -> 1.4734552 | L13: ='Farmer ROI'!$B$9-C13 -> 2793.3856 | M13: =IF(F13="","",F13/'Farmer ROI'!$B$9) | N13: =IF(F13="","",'Farmer ROI'!$B$9*12/F13) | O13: =IF(E13=0,"",B13/E13) -> 0.036730325 | P13: S1
A14: RainMaker Kubwa MAX + CSB2 | B14: 8099 | C14: 5900 | D14: 36 | E14: =B14+C14*D14 -> 220499 | G14: =IF(F14="","",1-B14/F14) | H14: =IF(F14="","",E14-F14) | I14: =IF(F14="","",H14/F14) | J14: =C14/'Farmer ROI'!$B$8 -> 0.24770349 | K14: ='Farmer ROI'!$B$9/C14 -> 1.4734552 | L14: ='Farmer ROI'!$B$9-C14 -> 2793.3856 | M14: =IF(F14="","",F14/'Farmer ROI'!$B$9) | N14: =IF(F14="","",'Farmer ROI'!$B$9*12/F14) | O14: =IF(E14=0,"",B14/E14) -> 0.036730325 | P14: S1
A15: Hydromax Solar + CSD2 | B15: 5199 | C15: 4900 | D15: 30 | E15: =B15+C15*D15 -> 152199 | G15: =IF(F15="","",1-B15/F15) | H15: =IF(F15="","",E15-F15) | I15: =IF(F15="","",H15/F15) | J15: =C15/'Farmer ROI'!$B$8 -> 0.20571985 | K15: ='Farmer ROI'!$B$9/C15 -> 1.7741603 | L15: ='Farmer ROI'!$B$9-C15 -> 3793.3856 | M15: =IF(F15="","",F15/'Farmer ROI'!$B$9) | N15: =IF(F15="","",'Farmer ROI'!$B$9*12/F15) | O15: =IF(E15=0,"",B15/E15) -> 0.034159226 | P15: S1
A17: Interpretation
A18: Point | B18: Why it matters
A19: Contractual collections ≠ profit | B19: The 85.6–95.1% premium on the three products with cash-price comparables must cover financing cost, time value of money, credit losses, collections, servicing, warranty and potentially installation. Do not present it as margin.
A20: Affordability result is benchmark-based | B20: The income benchmark is from a 2026 women-focused SunCulture Gender RBF assessment. It supports scenario testing, not a claim that every SunCulture borrower can afford every product.
A21: Repayment capacity is seasonal | B21: Monthly-equivalent income coverage is not the same as month-by-month liquidity. PAYGrow payments are monthly, while farm cash generation can be concentrated around harvests and exposed to climate shocks.
A22: Strategic implication | B22: PAYGrow materially reduces upfront cash barriers, but SunCulture carries a multi-year receivable plus servicing and credit risk. Scalable growth therefore depends on funding capacity, portfolio quality and underwriting discipline—not only product demand.
A24: Collection-Realization Stress Test — Gross Collections Relative to Cash Sale
A25: Collection Realization | B25: Gross Realized Collections / Cash Sale (x)
B26: 2S + CSD2 | C26: Kubwa MAX + CSD2 | D26: 2S MAX + CSD2
A27: 0.7 | B27: =$E$9*$A27/$F$9 -> 1.3030862 | C27: =$E$10*$A27/$F$10 -> 1.2992756 | D27: =$E$11*$A27/$F$11 -> 1.365906
A28: 0.8 | B28: =$E$9*$A28/$F$9 -> 1.4892414 | C28: =$E$10*$A28/$F$10 -> 1.4848864 | D28: =$E$11*$A28/$F$11 -> 1.5610354
A29: 0.9 | B29: =$E$9*$A29/$F$9 -> 1.6753965 | C29: =$E$10*$A29/$F$10 -> 1.6704972 | D29: =$E$11*$A29/$F$11 -> 1.7561648
A30: 1 | B30: =$E$9*$A30/$F$9 -> 1.8615517 | C30: =$E$10*$A30/$F$10 -> 1.856108 | D30: =$E$11*$A30/$F$11 -> 1.9512942
A31: Interpretation | B31: 1.00x means gross realized PAYGrow collections equal the stated cash-sale price. Values above 1.00x are not profit: funding cost, credit/collection losses, servicing, warranty, tax and time value of money remain unmodeled.
A32: External context | B32: GOGLA's 2026 PAYGo PERFORM framework centers repayment rate and customer ownership. Its broader PAYGo dataset reports 72% average repayment at 2× contract term, with wide firm variation; SHS portfolios are not directly comparable to productive-use irrigation assets. | G32: S8

Sheet Sources
A1: Sources & Assumptions
A2: ID | B2: Source / Date | C2: Type / Quality | D2: Data Used | E2: Limitation / Modeling Treatment | F2: URL / Reference
A3: S1 | B3: 2026 Energy in Emerging Markets Case Competition — SunCulture case (Sep 2026) | C3: Official competition source — High | D3: PAYGrow product deposit, monthly payment, tenor and cash prices; free delivery/installation terms. | E3: Primary source for competition pricing. Use case-provided pricing rather than live website pricing. | F3: User-supplied PDF: 2026 EEMCC Case_Final(1).pdf, pp. 24–26
A4: S2 | B4: CrossBoundary / Shell Foundation, Gender Results-Based Financing Pilot Final Report (Mar 2026) | C4: Program evaluation / 60 Decibels data — Medium-High | D4: SunCulture women-customer baseline monthly income = US$184; 79% reported income increase; weighted uplift among gainers = 46.2%; expected uplift across income-generating customers = 36.5%. | E4: Women-focused RBF program; not necessarily representative of all SunCulture customers. Used as an illustrative benchmark scenario, not a causal population estimate. | F4: https://shellfoundation.org/wp-content/uploads/2026/03/Gender-RBF-Final-Report-6-March-2026-vF.pdf
A5: S3 | B5: Central Bank of Kenya, Daily KES Exchange Rates (11 Sep 2026) | C5: Official central bank data — High | D5: USD/KES = 129.45, used to translate the external USD income benchmark into KES. | E5: Nearest directly verified official daily observation to the 14 Sep case-pricing baseline; translation only, with immaterial effect on conclusions. | F5: https://www.centralbank.go.ke/forex/
A6: S4 | B6: SunCulture Annual Letter 2021 (published Mar 2022) | C6: Company analysis — Medium | D6: Affordability illustration assumes a solar-irrigation repayment equal to 35.30% of monthly household income. | E6: Not a disclosed underwriting policy or external standard; used only as a heuristic sensitivity benchmark. | F6: https://sunculture.io/blog/2022/03/27/sunculture-annual-letter-2021/
A7: S5 | B7: Duke University / University of Nairobi, Evaluating the Adaptation Benefits of Smallholder Solar Irrigation Systems in Kenya (Jan 2026) | C7: Independent academic evaluation — High | D7: 753-household panel; used as a counterweight when interpreting income ROI claims. | E7: Study reports encouraging welfare/adaptation changes, but direct short-run effects on total income and agricultural output were limited or statistically insignificant. Therefore modeled income-return/payback metrics are explicitly illustrative. | F7: https://energyaccess.duke.edu/wp-content/uploads/2026/01/evaluating-adaptation-benefits-smallholder-solar-irrigation-systems-kenya.pdf
A8: S6 | B8: SunCulture / 60 Decibels impact survey (Apr 2021) | C8: Company-hosted third-party survey — Medium | D8: 150 customers; 76% reported improvements in money earned from farming; average engagement 8 months; average cultivated area 1.9 acres. | E8: Older, self-reported customer survey; used only as corroborating context, not as a model input. | F8: https://sunculture.io/blog/2021/04/16/impact-survey-sunculture-improved-life-of-150-customers/
A9: S7 | B9: Applied Energy (2025), GIS-based method for assessing the viability of solar-powered irrigation | C9: Peer-reviewed research — High | D9: Finds modeled solar irrigation LCOE of US$0.09–0.25/kWh and cheaper than diesel irrigation across Kenya. | E9: Not SunCulture-specific and does not provide product-specific farmer ROI; used as qualitative external validation only. | F9: https://www.sciencedirect.com/science/article/pii/S0306261924018440
A10: S8 | B10: GOGLA, PAYGo PERFORM / Measuring What Matters (2026) | C10: Industry KPI framework & aggregated portfolio data — Medium-High | D10: Repayment Rate and Customer Ownership Rate identified as core PAYGo KPIs; broader dataset average repayment rate at 2× contract term = 72%, with material firm variation. | E10: Off-grid solar PAYGo portfolios, not SunCulture irrigation. Used only to motivate collection-realization stress testing; not used as a SunCulture forecast. | F10: https://gogla.org/blog/measuring-what-matters-paygo-kpis-to-drive-smarter-growth-and-investment/
A11: S9 | B11: GOGLA, Keeping the Lights On (May 2025) | C11: Industry customer research — Medium | D11: Among PAYGo SHS customers struggling to pay in Kenya/Uganda, stable monthly income was uncommon and climate shocks frequently affected income. | E11: Study intentionally sampled struggling SHS customers and excluded larger productive-use systems. Used only to support caution around smooth monthly cash-flow assumptions. | F11: https://gogla.org/reports/keeping-the-lights-on/
